mcp_server_snowflake/__init__.py
mcp_server_snowflake/environment.py
mcp_server_snowflake/server.py
mcp_server_snowflake/server_utils.py
mcp_server_snowflake/utils.py
mcp_server_snowflake/cortex_services/prompts.py
mcp_server_snowflake/cortex_services/tools.py
mcp_server_snowflake/object_manager/objects.py
mcp_server_snowflake/object_manager/prompts.py
mcp_server_snowflake/object_manager/tools.py
mcp_server_snowflake/query_manager/prompts.py
mcp_server_snowflake/query_manager/tools.py
mcp_server_snowflake/semantic_manager/objects.py
mcp_server_snowflake/semantic_manager/prompts.py
mcp_server_snowflake/semantic_manager/tools.py
mcp_server_snowflake/tests/__init__.py
mcp_server_snowflake/tests/test_service_config.py
snowflake_labs_mcp-1.3.4.dist-info/METADATA
snowflake_labs_mcp-1.3.4.dist-info/WHEEL
snowflake_labs_mcp-1.3.4.dist-info/entry_points.txt
snowflake_labs_mcp-1.3.4.dist-info/licenses/LICENSE
snowflake_labs_mcp-1.3.4.dist-info/RECORD
