Metadata-Version: 2.4
Name: snowflake-labs-mcp
Version: 1.3.4
Summary: MCP server for Snowflake
Project-URL: Repository, https://github.com/Snowflake-Labs/mcp.git
Project-URL: Issues, https://github.com/Snowflake-Labs/mcp/issues
Author: Carlos Serrano, Jason Summer, Tyler White
License-File: LICENSE
Requires-Python: >=3.11
Requires-Dist: fastmcp<3.0.0,>=2.8.1
Requires-Dist: mcp[cli]<2.0.0,>=1.9.4
Requires-Dist: pydantic<3.0.0,>=2.11.4
Requires-Dist: pyyaml<7.0.0,>=6.0.2
Requires-Dist: requests<3.0.0,>=2.32.3
Requires-Dist: snowflake-connector-python<4.0.0,>=3.15.0
Requires-Dist: snowflake-core<2.0.0,>=1.0.0
Requires-Dist: sqlglot<30.0.0,>=27.8.0
